{
  "name": "world1",
  "regions": [
    {
      "name": "region1",
      "subregions": [
        {
          "name": "subregion1",
          "rooms": [
            {
              "name": "room1",
              "isStartRoom": false,
              "entities": [
                {
                  "name": "entity1",
                  "position": [0,0,0],
                  "texID": 0,
                  "eID": 0,
                  "components": [
                  ]
                }
              ]
            },
            {
              "name": "room2",
              "isStartRoom": false,
              "entities": [
                {
                  "name": "entity2",
                  "position": [0,0,0],
                  "texID": 0,
                  "eID": 0,
                  "components": [
                  ]
                }
              ]
            }
          ]
        }
      ]
    },
    {
      "name": "region2",
      "subregions": [
        {
          "name": "subregion1",
          "rooms": [
            {
              "name": "room1",
              "isStartRoom": false,
              "entities": [
                {
                  "name": "entity1",
                  "position": [0,0,0],
                  "texID": 0,
                  "eID": 0,
                  "components": [
                  ]
                }
              ]
            },
            {
              "name": "room2",
              "isStartRoom": false,
              "entities": [
                {
                  "name": "entity2",
                  "position": [0,0,0],
                  "texID": 0,
                  "eID": 0,
                  "components": [
                  ]
                }
              ]
            }
          ]
        }
      ]
    },
    {
      "name": "region3",
      "subregions": [
        {
          "name": "subregion1",
          "rooms": [
            {
              "name": "room1",
              "isStartRoom": false,
              "entities": [
                {
                  "name": "entity1",
                  "position": [0,0,0],
                  "texID": 0,
                  "eID": 0,
                  "components": [
                  ]
                }
              ]
            },
            {
              "name": "room2",
              "isStartRoom": true,
              "entities": [
                {
                  "name": "entity2",
                  "position": [0,0,0],
                  "texID": 0,
                  "eID": 0,
                  "components": [
                  ]
                }
              ],
              "tiles": [
                {
                  "name": "tile1",
                  "position": [0,0,0],
                  "texID": 0,
                  "tID": 0,
                  "components": [
                  ]
                },
                {
                  "name": "tile2",
                  "position": [10,0,0],
                  "texID": 0,
                  "tID": 0,
                  "components": [
                  ]
                }
              ]
            }
          ]
        }
      ]
    }
  ]
}